{
  "setting_id": "mpr_score_threshold",
  "name": "MPR Score Threshold",
  "description": "Minimum accumulated score required to generate a Market Price Ramping alert.",
  "value_type": "decimal",
  "default": 18,
  "match_type": "hierarchy",
  "overrides": [
    {
      "match": { "asset_class": "equity" },
      "value": 16,
      "priority": 1,
      "description": "Higher threshold for equity — high normal volume creates noise"
    },
    {
      "match": { "asset_class": "commodity" },
      "value": 14,
      "priority": 1,
      "description": "Moderate threshold for commodity instruments"
    },
    {
      "match": { "asset_class": "fixed_income" },
      "value": 7,
      "priority": 1,
      "description": "Lower threshold for fixed income — price movements more significant"
    },
    {
      "match": { "asset_class": "index" },
      "value": 6,
      "priority": 1,
      "description": "Moderate threshold for index instruments"
    }
  ]
}
